{
  "hash": "43280143ad0d5f5ba4c4f5923df49acb",
  "result": {
    "markdown": "# Results\n\n<!-- Here's some example analysis code: -->\n\n\n::: {.cell}\n\n```{.r .cell-code}\n# Note the path that we need to use to access our data files when rendering this document\nmy_data <- read.csv(here::here('src/data/raw_data/my_csv_file.csv'))\n```\n:::\n\n::: {.cell}\n\n```{.r .cell-code}\nplot(rnorm(10))\n```\n\n::: {.cell-output-display}\n![A plot of random numbers](_03_results_files/figure-docx/fig-demo-plot-1.png){#fig-demo-plot}\n:::\n:::\n\n\nFigure @fig-demo-plot shows how we can have a caption and cross-reference for a plot. Note that figure label and cross-references must both be prefixed with `fig-`\n\n\n::: {.cell}\n\n:::\n\n\nHere is an example of inline code 3.14 in the middle of a sentence.\n",
    "supporting": [
      "_03_results_files/figure-docx"
    ],
    "filters": [
      "rmarkdown/pagebreak.lua"
    ],
    "includes": {},
    "engineDependencies": {},
    "preserve": null,
    "postProcess": false
  }
}